easydollar/USD.py
easydollar/__init__.py
easydollar/examples.py
easydollar-1.0.2.dist-info/METADATA
easydollar-1.0.2.dist-info/RECORD
easydollar-1.0.2.dist-info/WHEEL
easydollar-1.0.2.dist-info/top_level.txt
