Metadata-Version: 2.1
Name: easydollar
Version: 1.0.2
Summary: A simple, light-weight data type for handling cash (in USD)
Home-page: https://github.com/SeanCPP/easydollar
Author: Sean Patrick Franklin
Author-email: sean.patrick516@gmail.com
License: UNKNOWN
Platform: UNKNOWN
Classifier: Programming Language :: Python :: 3.6
Classifier: License :: OSI Approved :: MIT License
Classifier: Operating System :: OS Independent
